MANIFEST.in
README.md
setup.py
prado/__init__.py
prado.egg-info/PKG-INFO
prado.egg-info/SOURCES.txt
prado.egg-info/dependency_links.txt
prado.egg-info/not-zip-safe
prado.egg-info/requires.txt
prado.egg-info/top_level.txt
prado/datasets/__init__.py
prado/datasets/assertion.py
prado/datasets/collates.py
prado/datasets/constants.py
prado/datasets/datasets.py
prado/datasets/transforms.py
prado/layers/__init__.py
prado/layers/prado_core.py
prado/layers/projected_embedding.py
prado/layers/convolutions/__init__.py
prado/layers/convolutions/projected_attention.py
prado/layers/convolutions/skipgram_convolution.py
prado/layers/embeddings/__init__.py
prado/layers/embeddings/assertion.py
prado/layers/embeddings/embedding.py
prado/layers/projections/__init__.py
prado/layers/projections/assertion.py
prado/layers/projections/projection_operator.py
prado/layers/projections/projector.py