Metadata-Version: 2.1
Name: prado
Version: 0.3.0
Summary: The PyTorch implementation of PRADO
Home-page: http://github.com/suflaj/prado
Author: Miljenko Šuflaj
Author-email: headsouldev@gmail.com
License: Apache License 2.0
Keywords: prado pytorch torch kaliamoorthi ai
Platform: UNKNOWN
Classifier: Development Status :: 3 - Alpha
Classifier: Environment :: GPU
Classifier: Intended Audience :: Science/Research
Classifier: License :: OSI Approved :: Apache Software License
Classifier: Natural Language :: English
Classifier: Programming Language :: Python :: 3.8
Classifier: Topic :: Scientific/Engineering :: Artificial Intelligence
